sbe/__init__.py
sbe-0.3.1.dist-info/LICENSE
sbe-0.3.1.dist-info/METADATA
sbe-0.3.1.dist-info/WHEEL
sbe-0.3.1.dist-info/top_level.txt
sbe-0.3.1.dist-info/RECORD
