Metadata-Version: 2.1
Name: sbe
Version: 0.3.1
Home-page: https://github.com/kizzx2/sbe-python
Author: Chris Yuen
Author-email: chris@kizzx2.com
License-File: LICENSE
Requires-Dist: lxml
Requires-Dist: bitstring
